{
  "milestones": [],
  "categories": [],
  "streamHistory": [
    {
      "startTime": "2025-01-24T01:34:34.181Z",
      "endTime": "2025-01-24T01:34:44.529Z",
      "duration": "0h 0m",
      "milestones": []
    },
    {
      "startTime": "2025-01-24T01:35:29.480Z",
      "endTime": "2025-01-24T01:52:52.078Z",
      "duration": "0h 17m",
      "milestones": []
    },
    {
      "startTime": "2025-01-24T02:25:03.228Z",
      "endTime": "2025-01-24T02:32:07.469Z",
      "duration": "0h 7m",
      "milestones": [],
      "analytics": {
        "totalInteractions": 1,
        "topTopics": [
          {
            "topic": "!followprotection",
            "count": 3
          },
          {
            "topic": "!recommendations",
            "count": 2
          },
          {
            "topic": "!suspicious",
            "count": 1
          }
        ],
        "chatMood": {
          "current": {
            "sentiment": "Negative",
            "energy": "Medium"
          },
          "distribution": [
            {
              "mood": "Positive",
              "count": 1
            },
            {
              "mood": "Negative",
              "count": 1
            }
          ]
        },
        "highlights": []
      }
    },
    {
      "startTime": "2025-01-24T03:28:00.740Z",
      "endTime": "2025-01-24T03:28:18.933Z",
      "duration": "0h 0m",
      "milestones": [],
      "analytics": {
        "totalInteractions": 1,
        "topTopics": [
          {
            "topic": "!followprotection",
            "count": 3
          },
          {
            "topic": "!recommendations",
            "count": 2
          },
          {
            "topic": "!suspicious",
            "count": 1
          },
          {
            "topic": "!roast",
            "count": 1
          },
          {
            "topic": "@pokemoncommunitygame",
            "count": 1
          }
        ],
        "chatMood": {
          "current": {
            "sentiment": "Neutral",
            "energy": "Medium"
          },
          "distribution": [
            {
              "mood": "Positive",
              "count": 1
            },
            {
              "mood": "Negative",
              "count": 1
            }
          ]
        },
        "highlights": [],
        "viewerStats": {
          "unique": 1,
          "returning": 0,
          "loyalty": {
            "New Friend": 1,
            "Regular": 0,
            "Loyal Viewer": 0,
            "Dedicated Fan": 0,
            "Stream Veteran": 0
          },
          "topViewers": [
            {
              "username": "pyro1121",
              "visits": 1,
              "level": "New Friend"
            }
          ]
        }
      }
    },
    {
      "startTime": "2025-01-24T03:31:05.962Z",
      "endTime": "2025-01-24T03:31:21.522Z",
      "duration": "0h 0m",
      "milestones": [],
      "analytics": {
        "totalInteractions": 2,
        "topTopics": [
          {
            "topic": "!followprotection",
            "count": 3
          },
          {
            "topic": "!recommendations",
            "count": 2
          },
          {
            "topic": "!suspicious",
            "count": 1
          },
          {
            "topic": "!roast",
            "count": 1
          },
          {
            "topic": "@pokemoncommunitygame",
            "count": 1
          },
          {
            "topic": "!insights",
            "count": 1
          }
        ],
        "chatMood": {
          "current": {
            "sentiment": "Neutral",
            "energy": "Medium"
          },
          "distribution": [
            {
              "mood": "Positive",
              "count": 1
            },
            {
              "mood": "Negative",
              "count": 1
            },
            {
              "mood": "Neutral",
              "count": 1
            }
          ]
        },
        "highlights": [],
        "viewerStats": {
          "unique": 1,
          "returning": 100,
          "loyalty": {
            "New Friend": 1,
            "Regular": 0,
            "Loyal Viewer": 0,
            "Dedicated Fan": 0,
            "Stream Veteran": 0
          },
          "topViewers": [
            {
              "username": "pyro1121",
              "visits": 2,
              "level": "New Friend"
            }
          ]
        }
      }
    },
    {
      "startTime": "2025-01-24T04:43:31.101Z",
      "endTime": "2025-01-24T04:48:03.057Z",
      "duration": "0h 4m",
      "milestones": [],
      "analytics": {
        "totalInteractions": 2,
        "topTopics": [
          {
            "topic": "!followprotection",
            "count": 3
          },
          {
            "topic": "!recommendations",
            "count": 2
          },
          {
            "topic": "!roast",
            "count": 2
          },
          {
            "topic": "@pokemoncommunitygame",
            "count": 2
          },
          {
            "topic": "!suspicious",
            "count": 1
          },
          {
            "topic": "!insights",
            "count": 1
          }
        ],
        "chatMood": {
          "current": {
            "sentiment": "Neutral",
            "energy": "Medium"
          },
          "distribution": [
            {
              "mood": "Positive",
              "count": 1
            },
            {
              "mood": "Negative",
              "count": 1
            },
            {
              "mood": "Neutral",
              "count": 1
            }
          ]
        },
        "highlights": [],
        "viewerStats": {
          "unique": 1,
          "returning": 100,
          "loyalty": {
            "New Friend": 1,
            "Regular": 0,
            "Loyal Viewer": 0,
            "Dedicated Fan": 0,
            "Stream Veteran": 0
          },
          "topViewers": [
            {
              "username": "pyro1121",
              "visits": 3,
              "level": "New Friend"
            }
          ]
        }
      }
    },
    {
      "startTime": "2025-01-24T04:48:12.623Z",
      "endTime": "2025-01-24T04:48:17.432Z",
      "duration": "0h 0m",
      "milestones": [],
      "analytics": {
        "totalInteractions": 2,
        "topTopics": [
          {
            "topic": "!followprotection",
            "count": 3
          },
          {
            "topic": "!recommendations",
            "count": 2
          },
          {
            "topic": "!roast",
            "count": 2
          },
          {
            "topic": "@pokemoncommunitygame",
            "count": 2
          },
          {
            "topic": "!suspicious",
            "count": 1
          },
          {
            "topic": "!insights",
            "count": 1
          }
        ],
        "chatMood": {
          "current": {
            "sentiment": "Neutral",
            "energy": "Medium"
          },
          "distribution": [
            {
              "mood": "Positive",
              "count": 1
            },
            {
              "mood": "Negative",
              "count": 1
            },
            {
              "mood": "Neutral",
              "count": 1
            }
          ]
        },
        "highlights": [],
        "viewerStats": {
          "unique": 1,
          "returning": 100,
          "loyalty": {
            "New Friend": 1,
            "Regular": 0,
            "Loyal Viewer": 0,
            "Dedicated Fan": 0,
            "Stream Veteran": 0
          },
          "topViewers": [
            {
              "username": "pyro1121",
              "visits": 3,
              "level": "New Friend"
            }
          ]
        }
      }
    }
  ],
  "viewerEngagement": {
    "20": {
      "averageViewers": 0,
      "chatActivity": 1,
      "samples": 1
    }
  },
  "contentAnalytics": {
    "successfulTitles": [],
    "popularCategories": [],
    "peakTimes": {},
    "highlights": []
  }
}